{
  "officials": [
    {
      "nombre": "Nicolás Posse",
      "cargo": "Jefe de Gabinete",
      "edad": 58,
      "estado_civil": "Soltero",
      "id": 1,
      "foto": "https://fotos.perfil.com/2023/09/15/nicolas-posse-1655066.jpg"
    },
    {
      "nombre": "Luis Caputo",
      "cargo": "Ministro de Economía",
      "edad": 58,
      "estado_civil": "Casado",
      "id": 2,
      "foto": "https://cnnespanol.cnn.com/wp-content/uploads/2023/12/luis-caputo.jpg?quality=100&strip=info"
    },
    {
      "nombre": "Guillermo Francos",
      "cargo": "Ministro del Interior",
      "edad": 73,
      "estado_civil": "Casado",
      "id": 3,
      "foto": "https://media.ambito.com/p/122ceeba43ad0f29ed5645377faa3cb0/adjuntos/239/imagenes/041/166/0041166358/guillermo-francos-1500jpg.jpg"
    },
    {
      "nombre": "Mariano Cúneo Libarona",
      "cargo": "Ministro de Justicia",
      "edad": 62,
      "estado_civil": "Casado",
      "id": 4,
      "foto": "https://tn.com.ar/resizer/lXFPjMhoDgkPKsO712XO7_HgPX4=/767x0/smart/filters:format(webp)/cloudfront-us-east-1.images.arcpublishing.com/artear/7HVMBUZLFZFQXEKWZ4GGFL4JNY.jpg"
    },
    {
      "nombre": "Sandra Pettovello",
      "cargo": "Ministra de Capital Humano",
      "edad": 55,
      "estado_civil": "Soltera",
      "id": 5,
      "foto": "https://www.clarin.com/img/2023/12/18/AMnpqrbAp_720x0__1.jpg"
    },
    {
      "nombre": "Guillermo Ferraro",
      "cargo": "Ministro de Infraestructura",
      "edad": 68,
      "estado_civil": "Casado",
      "id": 6,
      "foto": "https://images.pagina12.com.ar/styles/focal_content_1200x1050/public/2023-11/791834-791834-guillermo-20ferraro-20milei_0.jpeg?h=b3660f0d&itok=59soPw5-"
    },
    {
      "nombre": "Patricia Bullrich",
      "cargo": "Ministra de Seguridad",
      "edad": 67,
      "estado_civil": "Soltera",
      "id": 7,
      "foto": "https://fotos.perfil.com/2024/02/09/trim/987/555/patricia-bullrich-1753212.jpg"
    },
    {
      "nombre": "Diana Mondino",
      "cargo": "Ministra de Relaciones Exteriores",
      "edad": 65,
      "estado_civil": "Casada",
      "id": 8,
      "foto": "https://media.letrap.com.ar/p/a170623f6b8089511b002764dac575eb/adjuntos/349/imagenes/100/117/0100117541/790x0/smart/diana-mondinojpg.jpg"
    },
    {
      "nombre": "Luis Petri",
      "cargo": "Ministro de Defensa",
      "edad": 46,
      "estado_civil": "Casado",
      "id": 9,
      "foto": "https://media.lmneuquen.com/p/f073b4b63eba297de468e46885b2a362/adjuntos/195/imagenes/007/648/0007648018/770x0/smart/luis-petri-aclaro-la-cuestion-organizacional-dentro-del-ejercito.jpg"
    }
  ]
}
